finite-state-machines/moore/fsm_combi.v
/*
In a Moore FSM, the output is a function of the previous state only.
All Moore FSMs can be (trivially) converted to Mealy FSMs
simply by setting the output of every transition arrow
to the output of the state it is pointing to.
The reverse direction is not always possible without
introducing new states.

Implements the following Moore FSM:
A -> B, 1
B -> C, 1
C -> A, 1

A: 0
B: 0
C: 1

(output assignment logic is found in main.v)
*/
module fsm_combi (input inp, input [1:0] st, output [1:0] out_st, output out);
    parameter [1:0] A = 2'b00, B = 2'b01, C = 2'b10;

    reg [1:0] out_st_reg, out_reg;
    assign out = out_reg;
    assign out_st = out_st_reg;
    
    always @ *
    begin
        out_st_reg = st;
        out_reg = 1'b0;
        case(st)
            A: if(inp) out_st_reg = B;
            B: if(inp) out_st_reg = C;
            C: if(inp)
            begin
                out_st_reg = A;
                out_reg = 1'b1;
            end
            default: out_st_reg = A;
        endcase
    end
endmodule

finite-state-machines/moore/main.v
`include "fsm_combi.v"

module fsm(input inp, clk, rst, output out);
    wire [1:0] nst, st;
    reg [1:0] st_reg;
    assign st = st_reg;

    // Sequential Part: Creating Register for Next State
    // ! Cannot assign to wires within always blocks!
    always @ (posedge clk)
        if(rst)
            st_reg <= 2'b0; // We assume 0 is the default state
        else
            st_reg <= nst;
    
    // Combinational Part
    // ! No period before typename!
    fsm_combi combinational_part(.inp(inp), .st(st), .out_st(nst), .out(out));
endmodule

finite-state-machines/moore/main_tb.v
`timescale 1ns/1ps
`include "main.v"

module main_tb;
    parameter HALF_CYC = 5;

    wire x_w, clk_w, rst_w, out;
    reg x, clk, rst;
    assign x_w = x;
    assign clk_w = clk;
    assign rst_w = rst;
    fsm uut(.inp(x_w), .clk(clk_w), .rst(rst_w), .out(out));

    initial begin
        $dumpfile("main_tb.vcd");
        $dumpvars(0, main_tb);
    end

    integer i = 0;
    initial begin
        clk = 1'b1;
        for(i = 0; i < 20; i = i + 1)
        begin
            #(HALF_CYC) clk = ~clk;
        end
    end

    initial begin
        x = 1'b1;
        rst = 1'b0;

        #(10);

        #(17) rst = 1'b1;
        #(10) rst = 1'b0;

        #(10) x=1'b0;
        #(10) x=1'b1;
    end
endmodule

finite-state-machines/moore/main_tb.vcd
$date
	Wed Nov 19 00:32:15 2025
$end
$version
	Icarus Verilog
$end
$timescale
	1ps
$end
$scope module main_tb $end
$var wire 1 ! clk_w $end
$var wire 1 " rst_w $end
$var wire 1 # x_w $end
$var wire 1 $ out $end
$var parameter 32 % HALF_CYC $end
$var reg 1 & clk $end
$var reg 1 ' rst $end
$var reg 1 ( x $end
$var integer 32 ) i [31:0] $end
$scope module uut $end
$var wire 1 ! clk $end
$var wire 1 # inp $end
$var wire 1 " rst $end
$var wire 2 * st [1:0] $end
$var wire 1 $ out $end
$var wire 2 + nst [1:0] $end
$var reg 2 , st_reg [1:0] $end
$scope module combinational_part $end
$var wire 1 # inp $end
$var wire 2 - out_st [1:0] $end
$var wire 2 . st [1:0] $end
$var wire 1 $ out $end
$var parameter 2 / A $end
$var parameter 2 0 B $end
$var parameter 2 1 C $end
$var reg 2 2 out_reg [1:0] $end
$var reg 2 3 out_st_reg [1:0] $end
$upscope $end
$upscope $end
$upscope $end
$enddefinitions $end
$comment Show the parameter values. $end
$dumpall
b10 1
b1 0
b0 /
b101 %
$end
#0
$dumpvars
b0 3
b0 2
bx .
b0 -
bx ,
b0 +
bx *
b0 )
1(
0'
1&
0$
1#
0"
1!
$end
#5000
b1 )
0!
0&
#10000
b1 +
b1 -
b1 3
b0 *
b0 .
b0 ,
b10 )
1!
1&
#15000
b11 )
0!
0&
#20000
b10 +
b10 -
b10 3
b1 *
b1 .
b1 ,
b100 )
1!
1&
#25000
b101 )
0!
0&
#27000
1"
1'
#30000
b1 +
b1 -
b1 3
b0 *
b0 .
b0 ,
b110 )
1!
1&
#35000
b111 )
0!
0&
#37000
0"
0'
#40000
b10 +
b10 -
b10 3
b1 *
b1 .
b1 ,
b1000 )
1!
1&
#45000
b1001 )
0!
0&
#47000
b1 +
b1 -
b1 3
0#
0(
#50000
b1010 )
1!
1&
#55000
b1011 )
0!
0&
#57000
b10 +
b10 -
b10 3
1#
1(
#60000
1$
b1 2
b0 +
b0 -
b0 3
b10 *
b10 .
b10 ,
b1100 )
1!
1&
#65000
b1101 )
0!
0&
#70000
0$
b1 +
b1 -
b1 3
b0 2
b0 *
b0 .
b0 ,
b1110 )
1!
1&
#75000
b1111 )
0!
0&
#80000
b10 +
b10 -
b10 3
b1 *
b1 .
b1 ,
b10000 )
1!
1&
#85000
b10001 )
0!
0&
#90000
1$
b1 2
b0 +
b0 -
b0 3
b10 *
b10 .
b10 ,
b10010 )
1!
1&
#95000
b10011 )
0!
0&
#100000
0$
b1 +
b1 -
b1 3
b0 2
b0 *
b0 .
b0 ,
b10100 )
1!
1&
